{
  "disclaimer": "Usage subject to terms: https://openexchangerates.org/terms",
  "license": "https://openexchangerates.org/license",
  "timestamp": 1756141200,
  "base": "USD",
  "rates": {
    "AED": 3.67295,
    "ARS": 1349.9595,
    "AUD": 1.539273,
    "BDT": 121.675949,
    "BGN": 1.67388,
    "BHD": 0.377041,
    "BRL": 5.4064,
    "CAD": 1.38341,
    "CHF": 0.804158,
    "CLP": 963.71,
    "CNY": 7.1516,
    "COP": 4024.16,
    "CZK": 21.068573,
    "DKK": 6.40475,
    "EGP": 48.4957,
    "EUR": 0.858016,
    "GBP": 0.741389,
    "HKD": 7.811595,
    "HRK": 6.464343,
    "HUF": 340.799604,
    "IDR": 16258.823005,
    "ILS": 3.36365,
    "INR": 87.548391,
    "ISK": 123.04,
    "JPY": 147.53805882,
    "KRW": 1389.459446,
    "KWD": 0.305479,
    "MAD": 9.000868,
    "MXN": 18.639405,
    "MYR": 4.2064,
    "NGN": 1528.29,
    "NOK": 10.107778,
    "NZD": 1.705493,
    "PEN": 3.498066,
    "PHP": 56.696997,
    "PKR": 283.530339,
    "PLN": 3.65587,
    "QAR": 3.632578,
    "RON": 4.3365,
    "RUB": 80.696213,
    "SAR": 3.752027,
    "SEK": 9.560137,
    "SGD": 1.284335,
    "THB": 32.443667,
    "TRY": 40.9932,
    "TWD": 30.438958,
    "UAH": 41.457589,
    "USD": 1,
    "UYU": 39.998349,
    "VND": 26305.406216,
    "ZAR": 17.615333
  }
}