{
  "disclaimer": "Usage subject to terms: https://openexchangerates.org/terms",
  "license": "https://openexchangerates.org/license",
  "timestamp": 1755496800,
  "base": "USD",
  "rates": {
    "AED": 3.6725,
    "ARS": 1298.4889,
    "AUD": 1.53407,
    "BGN": 1.6708,
    "BHD": 0.376994,
    "BRL": 5.4034,
    "CAD": 1.380283,
    "CHF": 0.806005,
    "CLP": 961.538462,
    "CNY": 7.1799,
    "COP": 4045.758451,
    "CZK": 20.906932,
    "DKK": 6.37588,
    "EGP": 48.3327,
    "EUR": 0.854284,
    "GBP": 0.737398,
    "HKD": 7.826895,
    "HRK": 6.436378,
    "HUF": 337.175602,
    "IDR": 16186.479873,
    "ILS": 3.393808,
    "INR": 87.427886,
    "ISK": 122.32,
    "JPY": 147.38584615,
    "KRW": 1384.810697,
    "KWD": 0.305444,
    "MAD": 8.996133,
    "MXN": 18.72906,
    "MYR": 4.2225,
    "NGN": 1529.05,
    "NOK": 10.185426,
    "NZD": 1.684218,
    "PEN": 3.559456,
    "PHP": 57.039001,
    "PKR": 283.315583,
    "PLN": 3.637545,
    "QAR": 3.640768,
    "RON": 4.3262,
    "RUB": 79.696244,
    "SAR": 3.752537,
    "SEK": 9.548487,
    "SGD": 1.281988,
    "THB": 32.432,
    "TRY": 40.898454,
    "TWD": 29.9845,
    "UAH": 41.215053,
    "USD": 1,
    "UYU": 40.070284,
    "VND": 26284.663353,
    "ZAR": 17.573243
  }
}