{
  "disclaimer": "Usage subject to terms: https://openexchangerates.org/terms",
  "license": "https://openexchangerates.org/license",
  "timestamp": 1751454000,
  "base": "USD",
  "rates": {
    "AED": 3.672995,
    "ARS": 1206,
    "AUD": 1.523326,
    "BGN": 1.661405,
    "BHD": 0.376987,
    "BRL": 5.4823,
    "CAD": 1.364596,
    "CHF": 0.792482,
    "CLP": 928.63,
    "CNY": 7.1687,
    "COP": 4115.665449,
    "CZK": 20.94,
    "DKK": 6.34034,
    "EGP": 49.3081,
    "EUR": 0.849767,
    "GBP": 0.729723,
    "HKD": 7.849838,
    "HRK": 6.402524,
    "HUF": 338.86,
    "IDR": 16234.811318,
    "ILS": 3.371431,
    "INR": 85.670499,
    "ISK": 121.52,
    "JPY": 143.9229,
    "KRW": 1359.103585,
    "KWD": 0.305192,
    "MAD": 8.97785,
    "MXN": 18.733959,
    "MYR": 4.229,
    "NGN": 1534.51,
    "NOK": 10.090793,
    "NZD": 1.646676,
    "PEN": 3.54363,
    "PHP": 56.375005,
    "PKR": 283.834627,
    "PLN": 3.613458,
    "QAR": 3.637072,
    "RON": 4.3051,
    "RUB": 78.796333,
    "SAR": 3.750186,
    "SEK": 9.51536,
    "SGD": 1.27363,
    "THB": 32.423,
    "TRY": 39.796613,
    "TWD": 29.044182,
    "UAH": 41.85796,
    "USD": 1,
    "UYU": 39.964941,
    "VND": 26167.73563,
    "ZAR": 17.6617
  }
}