{
  "disclaimer": "Usage subject to terms: https://openexchangerates.org/terms",
  "license": "https://openexchangerates.org/license",
  "timestamp": 1750057200,
  "base": "USD",
  "rates": {
    "AED": 3.67235,
    "ARS": 1182.2398,
    "AUD": 1.537587,
    "BGN": 1.69493,
    "BHD": 0.377057,
    "BRL": 5.5512,
    "CAD": 1.35814,
    "CHF": 0.811736,
    "CLP": 927.708495,
    "CNY": 7.181,
    "COP": 4129.099211,
    "CZK": 21.42,
    "DKK": 6.444687,
    "EGP": 50.6308,
    "EUR": 0.864052,
    "GBP": 0.736067,
    "HKD": 7.849661,
    "HRK": 6.512564,
    "HUF": 347.452465,
    "IDR": 16277.684509,
    "ILS": 3.550552,
    "INR": 85.987446,
    "ISK": 124.43,
    "JPY": 144.23672222,
    "KRW": 1361.014307,
    "KWD": 0.305942,
    "MAD": 9.119803,
    "MXN": 18.90513,
    "MYR": 4.243,
    "NGN": 1545.49,
    "NOK": 9.879868,
    "NZD": 1.658401,
    "PEN": 3.600203,
    "PHP": 56.416003,
    "PKR": 282.7651,
    "PLN": 3.68575,
    "QAR": 3.638524,
    "RON": 4.34284,
    "RUB": 78.749312,
    "SAR": 3.7532,
    "SEK": 9.481115,
    "SGD": 1.2812,
    "THB": 32.466167,
    "TRY": 39.39478,
    "TWD": 29.511499,
    "UAH": 41.37256,
    "USD": 1,
    "UYU": 40.889225,
    "VND": 26085.822799,
    "ZAR": 17.85157
  }
}