{
  "disclaimer": "Usage subject to terms: https://openexchangerates.org/terms",
  "license": "https://openexchangerates.org/license",
  "timestamp": 1749841200,
  "base": "USD",
  "rates": {
    "AED": 3.6724,
    "ARS": 1182.2193,
    "AUD": 1.540774,
    "BGN": 1.6947,
    "BHD": 0.377172,
    "BRL": 5.535899,
    "CAD": 1.359369,
    "CHF": 0.811512,
    "CLP": 937.43,
    "CNY": 7.1816,
    "COP": 4140.467774,
    "CZK": 21.513481,
    "DKK": 6.46213,
    "EGP": 49.7334,
    "EUR": 0.866441,
    "GBP": 0.737314,
    "HKD": 7.84957,
    "HRK": 6.5271,
    "HUF": 349.0505,
    "IDR": 16295.968435,
    "ILS": 3.600315,
    "INR": 86.169007,
    "ISK": 124.76,
    "JPY": 143.95983333,
    "KRW": 1367.008792,
    "KWD": 0.306217,
    "MAD": 9.1145,
    "MXN": 18.943283,
    "MYR": 4.246,
    "NGN": 1543.02,
    "NOK": 9.904137,
    "NZD": 1.66164,
    "PEN": 3.6095,
    "PHP": 56.206,
    "PKR": 282.65,
    "PLN": 3.70091,
    "QAR": 3.6406,
    "RON": 4.35,
    "RUB": 79.825341,
    "SAR": 3.753504,
    "SEK": 9.498663,
    "SGD": 1.282192,
    "THB": 32.411,
    "TRY": 39.357499,
    "TWD": 29.573,
    "UAH": 41.51328,
    "USD": 1,
    "UYU": 41.099115,
    "VND": 26075,
    "ZAR": 17.942829
  }
}