{
  "disclaimer": "Usage subject to terms: https://openexchangerates.org/terms",
  "license": "https://openexchangerates.org/license",
  "timestamp": 1750996801,
  "base": "USD",
  "rates": {
    "AED": 3.67249,
    "ARS": 1188.4899,
    "AUD": 1.527135,
    "BGN": 1.67153,
    "BHD": 0.377223,
    "BRL": 5.480711,
    "CAD": 1.363999,
    "CHF": 0.800727,
    "CLP": 931.25,
    "CNY": 7.1709,
    "COP": 4066.233553,
    "CZK": 21.174501,
    "DKK": 6.37928,
    "EGP": 49.902316,
    "EUR": 0.854991,
    "GBP": 0.727992,
    "HKD": 7.849497,
    "HRK": 6.440558,
    "HUF": 341.963007,
    "IDR": 16208.25,
    "ILS": 3.39375,
    "INR": 85.565599,
    "ISK": 121.42,
    "JPY": 144.4580625,
    "KRW": 1356.012477,
    "KWD": 0.305761,
    "MAD": 9.069534,
    "MXN": 18.8687,
    "MYR": 4.2285,
    "NGN": 1547.89,
    "NOK": 10.089657,
    "NZD": 1.648259,
    "PEN": 3.580907,
    "PHP": 56.4975,
    "PKR": 284.169412,
    "PLN": 3.626821,
    "QAR": 3.663665,
    "RON": 4.3373,
    "RUB": 78.749386,
    "SAR": 3.750507,
    "SEK": 9.524234,
    "SGD": 1.274769,
    "THB": 32.537,
    "TRY": 39.836799,
    "TWD": 28.755,
    "UAH": 41.679185,
    "USD": 1,
    "UYU": 40.29492,
    "VND": 26092.629276,
    "ZAR": 17.86686
  }
}