{
  "disclaimer": "Usage subject to terms: https://openexchangerates.org/terms",
  "license": "https://openexchangerates.org/license",
  "timestamp": 1751518801,
  "base": "USD",
  "rates": {
    "AED": 3.673007,
    "ARS": 1206,
    "AUD": 1.522015,
    "BGN": 1.65803,
    "BHD": 0.376938,
    "BRL": 5.4271,
    "CAD": 1.359701,
    "CHF": 0.791886,
    "CLP": 925.69,
    "CNY": 7.1646,
    "COP": 4017.721067,
    "CZK": 20.915199,
    "DKK": 6.328915,
    "EGP": 49.351322,
    "EUR": 0.848206,
    "GBP": 0.733706,
    "HKD": 7.849965,
    "HRK": 6.390966,
    "HUF": 339.387088,
    "IDR": 16227.270993,
    "ILS": 3.371705,
    "INR": 85.609191,
    "ISK": 121.14,
    "JPY": 143.83866667,
    "KRW": 1360.081169,
    "KWD": 0.305249,
    "MAD": 8.964871,
    "MXN": 18.81013,
    "MYR": 4.224,
    "NGN": 1528.9,
    "NOK": 10.077836,
    "NZD": 1.647384,
    "PEN": 3.551846,
    "PHP": 56.327002,
    "PKR": 284.47639,
    "PLN": 3.616834,
    "QAR": 3.636002,
    "RON": 4.2941,
    "RUB": 78.924012,
    "SAR": 3.750281,
    "SEK": 9.530604,
    "SGD": 1.273315,
    "THB": 32.375557,
    "TRY": 39.917905,
    "TWD": 28.8795,
    "UAH": 41.641762,
    "USD": 1,
    "UYU": 39.459299,
    "VND": 26205.450734,
    "ZAR": 17.6174
  }
}