{
  "disclaimer": "Usage subject to terms: https://openexchangerates.org/terms",
  "license": "https://openexchangerates.org/license",
  "timestamp": 1757325600,
  "base": "USD",
  "rates": {
    "AED": 3.6725,
    "ARS": 1365.0175,
    "AUD": 1.519278,
    "BDT": 121.461209,
    "BGN": 1.667605,
    "BHD": 0.376982,
    "BRL": 5.4096,
    "CAD": 1.381785,
    "CHF": 0.796376,
    "CLP": 961.538462,
    "CNY": 7.1305,
    "COP": 3976.837001,
    "CZK": 20.79145,
    "DKK": 6.368149,
    "EGP": 48.18,
    "EUR": 0.852979,
    "GBP": 0.74024,
    "HKD": 7.793459,
    "HRK": 6.425892,
    "HUF": 335.525787,
    "IDR": 16525.341497,
    "ILS": 3.32592,
    "INR": 88.024495,
    "ISK": 121.97,
    "JPY": 147.754,
    "KRW": 1389.53806,
    "KWD": 0.305468,
    "MAD": 9.069422,
    "MXN": 18.695807,
    "MYR": 4.2191,
    "NGN": 1519.46,
    "NOK": 10.00096,
    "NZD": 1.688376,
    "PEN": 3.515453,
    "PHP": 56.823999,
    "PKR": 283.201235,
    "PLN": 3.627417,
    "QAR": 3.642603,
    "RON": 4.3248,
    "RUB": 81.874676,
    "SAR": 3.752159,
    "SEK": 9.394695,
    "SGD": 1.284222,
    "THB": 31.8655,
    "TRY": 41.250703,
    "TWD": 30.449801,
    "UAH": 41.139666,
    "USD": 1,
    "UYU": 40.166868,
    "VND": 26413.100898,
    "ZAR": 17.551217
  }
}