{
  "disclaimer": "Usage subject to terms: https://openexchangerates.org/terms",
  "license": "https://openexchangerates.org/license",
  "timestamp": 1750939200,
  "base": "USD",
  "rates": {
    "AED": 3.67252,
    "ARS": 1189.994955,
    "AUD": 1.530878,
    "BGN": 1.66797,
    "BHD": 0.377234,
    "BRL": 5.5591,
    "CAD": 1.368595,
    "CHF": 0.801878,
    "CLP": 937.4,
    "CNY": 7.1708,
    "COP": 4066.729696,
    "CZK": 21.1897,
    "DKK": 6.379266,
    "EGP": 49.8998,
    "EUR": 0.855077,
    "GBP": 0.729516,
    "HKD": 7.849785,
    "HRK": 6.441403,
    "HUF": 341.937032,
    "IDR": 16236.679431,
    "ILS": 3.39982,
    "INR": 85.74554,
    "ISK": 121.6,
    "JPY": 144.39016667,
    "KRW": 1355.761383,
    "KWD": 0.305839,
    "MAD": 9.061783,
    "MXN": 18.868035,
    "MYR": 4.229,
    "NGN": 1547.98,
    "NOK": 10.101901,
    "NZD": 1.652879,
    "PEN": 3.577848,
    "PHP": 56.696999,
    "PKR": 283.909603,
    "PLN": 3.63124,
    "QAR": 3.660362,
    "RON": 4.339705,
    "RUB": 78.494003,
    "SAR": 3.750486,
    "SEK": 9.475005,
    "SGD": 1.2756,
    "THB": 32.5005,
    "TRY": 39.776502,
    "TWD": 29.275499,
    "UAH": 41.643028,
    "USD": 1,
    "UYU": 40.259796,
    "VND": 26119.901434,
    "ZAR": 17.785335
  }
}