{
  "disclaimer": "Usage subject to terms: https://openexchangerates.org/terms",
  "license": "https://openexchangerates.org/license",
  "timestamp": 1755885600,
  "base": "USD",
  "rates": {
    "AED": 3.6725,
    "ARS": 1320.7162,
    "AUD": 1.539658,
    "BDT": 121.554044,
    "BGN": 1.67925,
    "BHD": 0.37706,
    "BRL": 5.4187,
    "CAD": 1.381878,
    "CHF": 0.80048,
    "CLP": 960.66,
    "CNY": 7.1657,
    "COP": 4008.97,
    "CZK": 20.905999,
    "DKK": 6.359655,
    "EGP": 48.4995,
    "EUR": 0.852008,
    "GBP": 0.73873,
    "HKD": 7.814057,
    "HRK": 6.418788,
    "HUF": 336.686957,
    "IDR": 16226.6,
    "ILS": 3.3686,
    "INR": 87.281703,
    "ISK": 122.19,
    "JPY": 146.64621429,
    "KRW": 1382.140769,
    "KWD": 0.30536,
    "MAD": 9.046609,
    "MXN": 18.60107,
    "MYR": 4.2275,
    "NGN": 1535.38,
    "NOK": 10.042459,
    "NZD": 1.70353,
    "PEN": 3.509732,
    "PHP": 56.455002,
    "PKR": 283.584454,
    "PLN": 3.629103,
    "QAR": 3.643487,
    "RON": 4.305,
    "RUB": 80.548303,
    "SAR": 3.752216,
    "SEK": 9.484743,
    "SGD": 1.28085,
    "THB": 32.37725,
    "TRY": 40.986,
    "TWD": 30.342998,
    "UAH": 41.313539,
    "USD": 1,
    "UYU": 40.070284,
    "VND": 26341.5,
    "ZAR": 17.443917
  }
}