{
  "disclaimer": "Usage subject to terms: https://openexchangerates.org/terms",
  "license": "https://openexchangerates.org/license",
  "timestamp": 1750136400,
  "base": "USD",
  "rates": {
    "AED": 3.672455,
    "ARS": 1182.2143,
    "AUD": 1.530182,
    "BGN": 1.691885,
    "BHD": 0.37705,
    "BRL": 5.4918,
    "CAD": 1.357284,
    "CHF": 0.81356,
    "CLP": 936.3,
    "CNY": 7.1812,
    "COP": 4120.17196,
    "CZK": 21.466399,
    "DKK": 6.451338,
    "EGP": 50.2599,
    "EUR": 0.864961,
    "GBP": 0.736747,
    "HKD": 7.84985,
    "HRK": 6.516234,
    "HUF": 348.168922,
    "IDR": 16269.212157,
    "ILS": 3.486315,
    "INR": 86.063288,
    "ISK": 124.21,
    "JPY": 144.594,
    "KRW": 1361.226169,
    "KWD": 0.305989,
    "MAD": 9.111176,
    "MXN": 18.929445,
    "MYR": 4.2405,
    "NGN": 1543.16,
    "NOK": 9.90304,
    "NZD": 1.648067,
    "PEN": 3.6025,
    "PHP": 56.648505,
    "PKR": 283.018277,
    "PLN": 3.697604,
    "QAR": 3.643443,
    "RON": 4.3423,
    "RUB": 78.496969,
    "SAR": 3.75189,
    "SEK": 9.483799,
    "SGD": 1.28084,
    "THB": 32.492504,
    "TRY": 39.396199,
    "TWD": 29.4425,
    "UAH": 41.557364,
    "USD": 1,
    "UYU": 41.082229,
    "VND": 26058.316182,
    "ZAR": 17.8244
  }
}