{
  "disclaimer": "Usage subject to terms: https://openexchangerates.org/terms",
  "license": "https://openexchangerates.org/license",
  "timestamp": 1752008400,
  "base": "USD",
  "rates": {
    "AED": 3.673,
    "ARS": 1254.232701,
    "AUD": 1.531255,
    "BGN": 1.66807,
    "BHD": 0.376945,
    "BRL": 5.449106,
    "CAD": 1.366138,
    "CHF": 0.795863,
    "CLP": 943.822491,
    "CNY": 7.17406,
    "COP": 4052.620416,
    "CZK": 21.032348,
    "DKK": 6.363158,
    "EGP": 49.679028,
    "EUR": 0.85283,
    "GBP": 0.735673,
    "HKD": 7.849902,
    "HRK": 6.42541,
    "HUF": 341.38926,
    "IDR": 16269.091438,
    "ILS": 3.354323,
    "INR": 85.71952,
    "ISK": 121.92,
    "JPY": 146.57728652,
    "KRW": 1370.093043,
    "KWD": 0.305428,
    "MAD": 9.002335,
    "MXN": 18.605547,
    "MYR": 4.241,
    "NGN": 1531.761492,
    "NOK": 10.09295,
    "NZD": 1.667165,
    "PEN": 3.563342,
    "PHP": 56.540667,
    "PKR": 284.177407,
    "PLN": 3.620198,
    "QAR": 3.641186,
    "RON": 4.329633,
    "RUB": 78.498896,
    "SAR": 3.750171,
    "SEK": 9.521279,
    "SGD": 1.279758,
    "THB": 32.568598,
    "TRY": 40.037758,
    "TWD": 29.122428,
    "UAH": 41.744944,
    "USD": 1,
    "UYU": 40.127651,
    "VND": 26130.135174,
    "ZAR": 17.791969
  }
}