{
  "disclaimer": "Usage subject to terms: https://openexchangerates.org/terms",
  "license": "https://openexchangerates.org/license",
  "timestamp": 1750384800,
  "base": "USD",
  "rates": {
    "AED": 3.672345,
    "ARS": 1164.5001,
    "AUD": 1.544173,
    "BGN": 1.698595,
    "BHD": 0.377329,
    "BRL": 5.49368,
    "CAD": 1.370017,
    "CHF": 0.816427,
    "CLP": 941.08,
    "CNY": 7.1796,
    "COP": 4054.6281,
    "CZK": 21.538989,
    "DKK": 6.478916,
    "EGP": 50.6755,
    "EUR": 0.868556,
    "GBP": 0.741879,
    "HKD": 7.849825,
    "HRK": 6.542353,
    "HUF": 350.246039,
    "IDR": 16363.35,
    "ILS": 3.492403,
    "INR": 86.636248,
    "ISK": 123.86,
    "JPY": 145.33828584,
    "KRW": 1372.653924,
    "KWD": 0.3063,
    "MAD": 9.154446,
    "MXN": 19.040477,
    "MYR": 4.2505,
    "NGN": 1547.29,
    "NOK": 10.027188,
    "NZD": 1.669352,
    "PEN": 3.593901,
    "PHP": 57.216499,
    "PKR": 283.423987,
    "PLN": 3.711399,
    "QAR": 3.641199,
    "RON": 4.3689,
    "RUB": 77.998034,
    "SAR": 3.752492,
    "SEK": 9.62731,
    "SGD": 1.285148,
    "THB": 32.7835,
    "TRY": 39.6665,
    "TWD": 29.587799,
    "UAH": 41.71924,
    "USD": 1,
    "UYU": 40.889225,
    "VND": 26126.718578,
    "ZAR": 18.009769
  }
}