{
  "disclaimer": "Usage subject to terms: https://openexchangerates.org/terms",
  "license": "https://openexchangerates.org/license",
  "timestamp": 1750194000,
  "base": "USD",
  "rates": {
    "AED": 3.672422,
    "ARS": 1162.500318,
    "AUD": 1.544283,
    "BGN": 1.68999,
    "BHD": 0.377038,
    "BRL": 5.499736,
    "CAD": 1.367841,
    "CHF": 0.816369,
    "CLP": 944.720491,
    "CNY": 7.185,
    "COP": 4114.619488,
    "CZK": 21.622263,
    "DKK": 6.496395,
    "EGP": 50.1484,
    "EUR": 0.871062,
    "GBP": 0.74471,
    "HKD": 7.849732,
    "HRK": 6.562385,
    "HUF": 351.903125,
    "IDR": 16336.128629,
    "ILS": 3.512652,
    "INR": 86.502881,
    "ISK": 125.035,
    "JPY": 145.27533642,
    "KRW": 1381.561921,
    "KWD": 0.30619,
    "MAD": 9.115188,
    "MXN": 19.012814,
    "MYR": 4.2455,
    "NGN": 1544.953341,
    "NOK": 9.942165,
    "NZD": 1.662548,
    "PEN": 3.605972,
    "PHP": 56.984114,
    "PKR": 283.254211,
    "PLN": 3.724973,
    "QAR": 3.641624,
    "RON": 4.379766,
    "RUB": 78.519734,
    "SAR": 3.751987,
    "SEK": 9.555619,
    "SGD": 1.286253,
    "THB": 32.602958,
    "TRY": 39.486149,
    "TWD": 29.663773,
    "UAH": 41.534469,
    "USD": 1,
    "UYU": 40.984695,
    "VND": 26080.26171,
    "ZAR": 18.024074
  }
}