{
  "disclaimer": "Usage subject to terms: https://openexchangerates.org/terms",
  "license": "https://openexchangerates.org/license",
  "timestamp": 1754604000,
  "base": "USD",
  "rates": {
    "AED": 3.673,
    "ARS": 1326.2387,
    "AUD": 1.533783,
    "BGN": 1.6768,
    "BHD": 0.376987,
    "BRL": 5.4172,
    "CAD": 1.374669,
    "CHF": 0.805999,
    "CLP": 970.33,
    "CNY": 7.1815,
    "COP": 4051.660244,
    "CZK": 20.970531,
    "DKK": 6.398118,
    "EGP": 48.5445,
    "EUR": 0.857201,
    "GBP": 0.743986,
    "HKD": 7.849407,
    "HRK": 6.459021,
    "HUF": 340.220975,
    "IDR": 16304.6,
    "ILS": 3.4252,
    "INR": 87.41095,
    "ISK": 122.42,
    "JPY": 147.057,
    "KRW": 1383.719938,
    "KWD": 0.305521,
    "MAD": 9.051132,
    "MXN": 18.616802,
    "MYR": 4.2316,
    "NGN": 1530.06,
    "NOK": 10.224844,
    "NZD": 1.677887,
    "PEN": 3.559138,
    "PHP": 57.105,
    "PKR": 283.593656,
    "PLN": 3.647385,
    "QAR": 3.642292,
    "RON": 4.347,
    "RUB": 79.250132,
    "SAR": 3.752779,
    "SEK": 9.566511,
    "SGD": 1.283201,
    "THB": 32.320002,
    "TRY": 40.665201,
    "TWD": 29.815201,
    "UAH": 41.495676,
    "USD": 1,
    "UYU": 40.163639,
    "VND": 26212.321591,
    "ZAR": 17.72101
  }
}