{
  "disclaimer": "Usage subject to terms: https://openexchangerates.org/terms",
  "license": "https://openexchangerates.org/license",
  "timestamp": 1751007600,
  "base": "USD",
  "rates": {
    "AED": 3.6725,
    "ARS": 1188.49496,
    "AUD": 1.525777,
    "BGN": 1.6729,
    "BHD": 0.37728,
    "BRL": 5.4805,
    "CAD": 1.363049,
    "CHF": 0.799693,
    "CLP": 931.49,
    "CNY": 7.1665,
    "COP": 4058.89002,
    "CZK": 21.115622,
    "DKK": 6.366735,
    "EGP": 49.899524,
    "EUR": 0.853326,
    "GBP": 0.727409,
    "HKD": 7.849803,
    "HRK": 6.432372,
    "HUF": 340.930399,
    "IDR": 16187.832351,
    "ILS": 3.3897,
    "INR": 85.53886,
    "ISK": 121.17,
    "JPY": 144.24064286,
    "KRW": 1356.322389,
    "KWD": 0.305778,
    "MAD": 9.069534,
    "MXN": 18.86091,
    "MYR": 4.2285,
    "NGN": 1548,
    "NOK": 10.073736,
    "NZD": 1.646538,
    "PEN": 3.580907,
    "PHP": 56.500493,
    "PKR": 284.169412,
    "PLN": 3.621289,
    "QAR": 3.663665,
    "RON": 4.3289,
    "RUB": 78.522299,
    "SAR": 3.750486,
    "SEK": 9.493487,
    "SGD": 1.273752,
    "THB": 32.5504,
    "TRY": 39.885202,
    "TWD": 28.844857,
    "UAH": 41.679185,
    "USD": 1,
    "UYU": 40.29492,
    "VND": 26099.439307,
    "ZAR": 17.782504
  }
}