{
  "disclaimer": "Usage subject to terms: https://openexchangerates.org/terms",
  "license": "https://openexchangerates.org/license",
  "timestamp": 1756414800,
  "base": "USD",
  "rates": {
    "AED": 3.6725,
    "ARS": 1334.006213,
    "AUD": 1.530885,
    "BDT": 121.669049,
    "BGN": 1.675339,
    "BHD": 0.377022,
    "BRL": 5.412534,
    "CAD": 1.37492,
    "CHF": 0.801416,
    "CLP": 969.381893,
    "CNY": 7.146233,
    "COP": 4021.373587,
    "CZK": 21.004425,
    "DKK": 6.389712,
    "EGP": 48.499268,
    "EUR": 0.855964,
    "GBP": 0.74008,
    "HKD": 7.794188,
    "HRK": 6.450304,
    "HUF": 339.654185,
    "IDR": 16354.487403,
    "ILS": 3.325194,
    "INR": 87.599007,
    "ISK": 122.41,
    "JPY": 146.94649965,
    "KRW": 1385.585952,
    "KWD": 0.305589,
    "MAD": 9.021153,
    "MXN": 18.651412,
    "MYR": 4.217,
    "NGN": 1537.933066,
    "NOK": 10.068282,
    "NZD": 1.699429,
    "PEN": 3.55286,
    "PHP": 56.894164,
    "PKR": 283.735808,
    "PLN": 3.651034,
    "QAR": 3.657273,
    "RON": 4.34166,
    "RUB": 80.502622,
    "SAR": 3.752163,
    "SEK": 9.480713,
    "SGD": 1.282217,
    "THB": 32.272799,
    "TRY": 41.0382,
    "TWD": 30.495685,
    "UAH": 41.246609,
    "USD": 1,
    "UYU": 40.034584,
    "VND": 26374.898586,
    "ZAR": 17.695968
  }
}