{
  "disclaimer": "Usage subject to terms: https://openexchangerates.org/terms",
  "license": "https://openexchangerates.org/license",
  "timestamp": 1755586800,
  "base": "USD",
  "rates": {
    "AED": 3.6725,
    "ARS": 1292.7556,
    "AUD": 1.540648,
    "BDT": 121.455385,
    "BGN": 1.67757,
    "BHD": 0.377013,
    "BRL": 5.4382,
    "CAD": 1.380404,
    "CHF": 0.806114,
    "CLP": 964.16,
    "CNY": 7.1818,
    "COP": 4017.408485,
    "CZK": 20.9512,
    "DKK": 6.393574,
    "EGP": 48.411261,
    "EUR": 0.856574,
    "GBP": 0.739941,
    "HKD": 7.795502,
    "HRK": 6.455818,
    "HUF": 337.722176,
    "IDR": 16250.128605,
    "ILS": 3.37927,
    "INR": 87.106888,
    "ISK": 122.84,
    "JPY": 147.6035,
    "KRW": 1388.953219,
    "KWD": 0.305633,
    "MAD": 9.010942,
    "MXN": 18.79645,
    "MYR": 4.224,
    "NGN": 1535.13,
    "NOK": 10.199783,
    "NZD": 1.687379,
    "PEN": 3.558078,
    "PHP": 57.1125,
    "PKR": 282,
    "PLN": 3.633308,
    "QAR": 3.64075,
    "RON": 4.3335,
    "RUB": 80.498965,
    "SAR": 3.752578,
    "SEK": 9.54467,
    "SGD": 1.283357,
    "THB": 32.5005,
    "TRY": 40.881702,
    "TWD": 30.100001,
    "UAH": 41.223012,
    "USD": 1,
    "UYU": 40.070284,
    "VND": 26301.946344,
    "ZAR": 17.629823
  }
}