{
  "disclaimer": "Usage subject to terms: https://openexchangerates.org/terms",
  "license": "https://openexchangerates.org/license",
  "timestamp": 1758610800,
  "base": "USD",
  "rates": {
    "AED": 3.6725,
    "ARS": 1410.25,
    "AUD": 1.516866,
    "BDT": 121.705825,
    "BGN": 1.6573,
    "BHD": 0.377021,
    "BRL": 5.3347,
    "CAD": 1.383131,
    "CHF": 0.792434,
    "CLP": 955.5,
    "CNY": 7.1128,
    "COP": 3858.56399,
    "CZK": 20.54886,
    "DKK": 6.328096,
    "EGP": 48.1838,
    "EUR": 0.847817,
    "GBP": 0.739851,
    "HKD": 7.773878,
    "HRK": 6.386499,
    "HUF": 329.788558,
    "IDR": 16664.640393,
    "ILS": 3.348767,
    "INR": 88.705096,
    "ISK": 120.89,
    "JPY": 147.71665,
    "KRW": 1394.001369,
    "KWD": 0.30531,
    "MAD": 9.024403,
    "MXN": 18.374875,
    "MYR": 4.198,
    "NGN": 1489.64,
    "NOK": 9.931057,
    "NZD": 1.707592,
    "PEN": 3.489678,
    "PHP": 57.190504,
    "PKR": 281.5,
    "PLN": 3.609355,
    "QAR": 3.64,
    "RON": 4.3027,
    "RUB": 83.870353,
    "SAR": 3.750737,
    "SEK": 9.362912,
    "SGD": 1.283401,
    "THB": 31.869198,
    "TRY": 41.422383,
    "TWD": 30.255998,
    "UAH": 41.357916,
    "USD": 1,
    "UYU": 39.823107,
    "VND": 26416.590079,
    "ZAR": 17.367023
  }
}