{
  "disclaimer": "Usage subject to terms: https://openexchangerates.org/terms",
  "license": "https://openexchangerates.org/license",
  "timestamp": 1753250400,
  "base": "USD",
  "rates": {
    "AED": 3.67302,
    "ARS": 1255.5118,
    "AUD": 1.522952,
    "BGN": 1.66598,
    "BHD": 0.376997,
    "BRL": 5.5649,
    "CAD": 1.360998,
    "CHF": 0.794243,
    "CLP": 950.73,
    "CNY": 7.1629,
    "COP": 4034.335262,
    "CZK": 20.990243,
    "DKK": 6.36357,
    "EGP": 49.0608,
    "EUR": 0.852476,
    "GBP": 0.739481,
    "HKD": 7.849925,
    "HRK": 6.423388,
    "HUF": 340.344646,
    "IDR": 16303.953747,
    "ILS": 3.33875,
    "INR": 86.392646,
    "ISK": 121.41,
    "JPY": 147.16425,
    "KRW": 1380.100172,
    "KWD": 0.30522,
    "MAD": 8.974611,
    "MXN": 18.643801,
    "MYR": 4.2275,
    "NGN": 1526,
    "NOK": 10.073241,
    "NZD": 1.662386,
    "PEN": 3.546958,
    "PHP": 56.953999,
    "PKR": 283.893503,
    "PLN": 3.62525,
    "QAR": 3.631913,
    "RON": 4.3217,
    "RUB": 78.498674,
    "SAR": 3.751422,
    "SEK": 9.519646,
    "SGD": 1.278773,
    "THB": 32.2,
    "TRY": 40.446899,
    "TWD": 29.362499,
    "UAH": 41.616771,
    "USD": 1,
    "UYU": 40.199167,
    "VND": 26133.542848,
    "ZAR": 17.5498
  }
}