{
  "disclaimer": "Usage subject to terms: https://openexchangerates.org/terms",
  "license": "https://openexchangerates.org/license",
  "timestamp": 1757952000,
  "base": "USD",
  "rates": {
    "AED": 3.6725,
    "ARS": 1466.427949,
    "AUD": 1.49918,
    "BDT": 121.680156,
    "BGN": 1.6633,
    "BHD": 0.377083,
    "BRL": 5.3098,
    "CAD": 1.379884,
    "CHF": 0.793811,
    "CLP": 950.25,
    "CNY": 7.1191,
    "COP": 3889.699175,
    "CZK": 20.64686,
    "DKK": 6.341737,
    "EGP": 48.1725,
    "EUR": 0.849508,
    "GBP": 0.734923,
    "HKD": 7.778463,
    "HRK": 6.401656,
    "HUF": 330.747313,
    "IDR": 16367.255352,
    "ILS": 3.35054,
    "INR": 88.136932,
    "ISK": 121.65,
    "JPY": 147.27242857,
    "KRW": 1385.192877,
    "KWD": 0.305225,
    "MAD": 8.992477,
    "MXN": 18.340338,
    "MYR": 4.205,
    "NGN": 1500.31,
    "NOK": 9.834116,
    "NZD": 1.674898,
    "PEN": 3.491041,
    "PHP": 57.103602,
    "PKR": 283.461732,
    "PLN": 3.608836,
    "QAR": 3.655339,
    "RON": 4.301,
    "RUB": 82.654207,
    "SAR": 3.751047,
    "SEK": 9.268377,
    "SGD": 1.280125,
    "THB": 31.7725,
    "TRY": 41.295494,
    "TWD": 30.188833,
    "UAH": 41.229084,
    "USD": 1,
    "UYU": 40.120608,
    "VND": 26385.362137,
    "ZAR": 17.379896
  }
}