{
  "disclaimer": "Usage subject to terms: https://openexchangerates.org/terms",
  "license": "https://openexchangerates.org/license",
  "timestamp": 1751378400,
  "base": "USD",
  "rates": {
    "AED": 3.673,
    "ARS": 1195.891825,
    "AUD": 1.521155,
    "BGN": 1.65625,
    "BHD": 0.37709,
    "BRL": 5.44575,
    "CAD": 1.363577,
    "CHF": 0.789324,
    "CLP": 924.78,
    "CNY": 7.163,
    "COP": 4079.24,
    "CZK": 20.916453,
    "DKK": 6.320175,
    "EGP": 49.41,
    "EUR": 0.847213,
    "GBP": 0.728014,
    "HKD": 7.849971,
    "HRK": 6.383623,
    "HUF": 338.336218,
    "IDR": 16217.986675,
    "ILS": 3.37184,
    "INR": 85.559169,
    "ISK": 120.62,
    "JPY": 143.09233333,
    "KRW": 1354.328057,
    "KWD": 0.305189,
    "MAD": 8.976481,
    "MXN": 18.709025,
    "MYR": 4.1975,
    "NGN": 1534.57,
    "NOK": 10.050065,
    "NZD": 1.639837,
    "PEN": 3.54309,
    "PHP": 56.325002,
    "PKR": 283.795064,
    "PLN": 3.596516,
    "QAR": 3.636487,
    "RON": 4.2956,
    "RUB": 78.530606,
    "SAR": 3.750392,
    "SEK": 9.472586,
    "SGD": 1.272245,
    "THB": 32.43,
    "TRY": 39.8359,
    "TWD": 29.264,
    "UAH": 41.852115,
    "USD": 1,
    "UYU": 39.958509,
    "VND": 26130.144095,
    "ZAR": 17.59885
  }
}