{
  "disclaimer": "Usage subject to terms: https://openexchangerates.org/terms",
  "license": "https://openexchangerates.org/license",
  "timestamp": 1753336800,
  "base": "USD",
  "rates": {
    "AED": 3.67299,
    "ARS": 1258.5117,
    "AUD": 1.510449,
    "BGN": 1.66086,
    "BHD": 0.376959,
    "BRL": 5.5166,
    "CAD": 1.360198,
    "CHF": 0.792481,
    "CLP": 948.21,
    "CNY": 7.1527,
    "COP": 4057.568882,
    "CZK": 20.889999,
    "DKK": 6.340806,
    "EGP": 49.0957,
    "EUR": 0.849555,
    "GBP": 0.736489,
    "HKD": 7.84953,
    "HRK": 6.399668,
    "HUF": 338.613169,
    "IDR": 16278.68665,
    "ILS": 3.33026,
    "INR": 86.317218,
    "ISK": 120.81,
    "JPY": 146.01322727,
    "KRW": 1366.110808,
    "KWD": 0.305016,
    "MAD": 8.962021,
    "MXN": 18.536269,
    "MYR": 4.2175,
    "NGN": 1524.55,
    "NOK": 10.106855,
    "NZD": 1.65135,
    "PEN": 3.552007,
    "PHP": 56.612498,
    "PKR": 283.704451,
    "PLN": 3.611421,
    "QAR": 3.632864,
    "RON": 4.3059,
    "RUB": 78.401028,
    "SAR": 3.751709,
    "SEK": 9.50828,
    "SGD": 1.275535,
    "THB": 32.25,
    "TRY": 40.471067,
    "TWD": 29.269,
    "UAH": 41.668885,
    "USD": 1,
    "UYU": 39.998349,
    "VND": 26143.79085,
    "ZAR": 17.531391
  }
}